japanese2phoneme/__init__.py
japanese2phoneme/core.py
japanese2phoneme/exceptions.py
japanese2phoneme/kana.py
japanese2phoneme/normalize.py
japanese2phoneme/data/hiraganaChart.txt
japanese2phoneme/data/katakanaChart.txt
japanese2phoneme-0.0.1.dist-info/LICENSE
japanese2phoneme-0.0.1.dist-info/METADATA
japanese2phoneme-0.0.1.dist-info/WHEEL
japanese2phoneme-0.0.1.dist-info/top_level.txt
japanese2phoneme-0.0.1.dist-info/RECORD
