Metadata-Version: 2.1
Name: japanese2phoneme
Version: 0.0.1
Summary: A python library
Home-page: https://github.com/iory/japanese2phoneme
Author: iory
Author-email: ab.ioryz@gmail.com
License: MIT
Platform: UNKNOWN
Classifier: Development Status :: 5 - Production/Stable
Classifier: Intended Audience :: Developers
Classifier: Natural Language :: English
Classifier: License :: OSI Approved :: MIT License
Classifier: Programming Language :: Python
Classifier: Programming Language :: Python :: 3.6
Classifier: Programming Language :: Python :: 3.7
License-File: LICENSE
Requires-Dist: ginza
Requires-Dist: ja-ginza
Requires-Dist: pybsc (>=0.0.8)
Requires-Dist: spacy
